anomaly_detection/.DS_Store
anomaly_detection/__init__.py
anomaly_detection/ad_execute.py
anomaly_detection/configs.py
anomaly_detection/create_api.py
anomaly_detection/dashboard.py
anomaly_detection/data_access.py
anomaly_detection/docker-compose.yml
anomaly_detection/dockerfile
anomaly_detection/dockerfile2
anomaly_detection/functions.py
anomaly_detection/iforest_model.py
anomaly_detection/instance.yaml
anomaly_detection/jobs.ipynb
anomaly_detection/logger.py
anomaly_detection/main.py
anomaly_detection/ml_executor.py
anomaly_detection/model_api.py
anomaly_detection/prophet_model.py
anomaly_detection/requirements.txt
anomaly_detection/requirements_pip.txt
anomaly_detection/requirements_pip2.txt
anomaly_detection/train_v2.py
anomaly_detection/utils.py
anomaly_detection/__pycache__/__init__.cpython-37.pyc
anomaly_detection/__pycache__/configs.cpython-37.pyc
anomaly_detection/__pycache__/data_access.cpython-37.pyc
anomaly_detection/__pycache__/functions.cpython-37.pyc
anomaly_detection/__pycache__/iforest_model.cpython-37.pyc
anomaly_detection/__pycache__/logger.cpython-37.pyc
anomaly_detection/__pycache__/prophet_model.cpython-37.pyc
anomaly_detection/__pycache__/train_v2.cpython-37.pyc
anomaly_detection/__pycache__/utils.cpython-37.pyc
anomaly_detection/data/.DS_Store
anomaly_detection/docs/.DS_Store
anomaly_detection/docs/apis.yaml
anomaly_detection/docs/configs.yaml
anomaly_detection/docs/ml_execute.yaml
anomaly_detection/docs/parameter_tunning.yaml
anomaly_detection/logs/.DS_Store
anomaly_detection/logs/process.yaml
anomaly_detection/logs/train_logfile_202006072239.log
anomaly_detection/logs/train_logfile_202006072243.log
anomaly_detection/models/.DS_Store
anomaly_detection/models/model_configuration.yaml
anomaly_detection/web/.DS_Store
anomaly_detection/web/main.py
anomaly_detection/web/updates.py
anomaly_detection/web/__pycache__/main.cpython-37.pyc
anomaly_detection/web/__pycache__/updates.cpython-37.pyc
anomaly_detection/web/css/main.css
anomaly_detection_framework-0.0.20.dist-info/LICENSE
anomaly_detection_framework-0.0.20.dist-info/METADATA
anomaly_detection_framework-0.0.20.dist-info/WHEEL
anomaly_detection_framework-0.0.20.dist-info/top_level.txt
anomaly_detection_framework-0.0.20.dist-info/RECORD
