Metadata-Version: 2.1
Name: anomaly-detection-framework
Version: 0.0.20
Summary: Anomaly Detection Framework allows us to calculate Anomalities on any Time - Series Data Sets. It has an interface which is easy to manage to train - predict with given dataset.
Home-page: https://github.com/caglanakpinar/tsad
Author: Caglan Akpinar
Author-email: cakpinar23@gmail.com
License: UNKNOWN
Keywords: anomaly Time Series Anomaly LSTM Prophet Isolation Forest
Platform: UNKNOWN
Classifier: Programming Language :: Python :: 3
Classifier: License :: OSI Approved :: MIT License
Classifier: Operating System :: OS Independent
Requires-Python: >=3.6
Requires-Dist: requests
Requires-Dist: docker-compose (>=1.25.5)
Requires-Dist: numpy (>=1.18.1)
Requires-Dist: pandas (>=0.25.3)
Requires-Dist: scipy (>=1.4.1)
Requires-Dist: tensorflow (>=2.2.0)
Requires-Dist: PyYAML
Requires-Dist: schedule (>=0.6.0)
Requires-Dist: scikit-learn (>=0.22.1)
Requires-Dist: DateTime (>=4.3)
Requires-Dist: Flask (>=1.1.1)
Requires-Dist: multiprocess (>=0.70.9)
Requires-Dist: google-cloud-bigquery
Requires-Dist: mysql-connector-python
Requires-Dist: plotly (>=4.5.0)
Requires-Dist: dash-html-components (>=1.0.2)
Requires-Dist: dash-core-components (>=1.8.0)
Requires-Dist: dash (>=1.9.0)
Requires-Dist: threaded (>=4.0.8)
Requires-Dist: requests (>=2.23.0)
Requires-Dist: pytest-shutil (>=1.7.0)
Requires-Dist: python-dateutil (>=2.8.1)
Requires-Dist: sockets (>=1.0.0)
Requires-Dist: random2 (>=1.0.1)
Requires-Dist: psycopg2 (>=2.8.5)
Requires-Dist: convertdate
Requires-Dist: LunarCalendar
Requires-Dist: holidays
Requires-Dist: pystan
Requires-Dist: fbprophet (==0.6)
Requires-Dist: Keras (>=2.3.1)
